extism/__init__.py
extism/extism.py
extism-1.0.4.dist-info/LICENSE
extism-1.0.4.dist-info/METADATA
extism-1.0.4.dist-info/WHEEL
extism-1.0.4.dist-info/RECORD
