Metadata-Version: 2.3
Name: extism
Version: 1.0.4
Summary: Extism Host SDK for python
License: BSD-3-Clause
Author: The Extism Authors
Author-email: oss@extism.org
Requires-Python: >=3.9
Classifier: License :: OSI Approved :: BSD License
Classifier: Programming Language :: Python :: 3
Classifier: Programming Language :: Python :: 3.9
Classifier: Programming Language :: Python :: 3.10
Classifier: Programming Language :: Python :: 3.11
Classifier: Programming Language :: Python :: 3.12
Classifier: Programming Language :: Python :: 3.13
Requires-Dist: extism-sys (>=1.9.1)
